change/__init__.py
change/__main__.py
change/_core.py
change/log.py
change_log-0.2.0.dist-info/LICENSE
change_log-0.2.0.dist-info/WHEEL
change_log-0.2.0.dist-info/METADATA
change_log-0.2.0.dist-info/RECORD
